pyxml2xpath-0.3.5.dist-info/licenses/LICENSE
xml2xpath/__init__.py
xml2xpath/xml2xpath.py
pyxml2xpath-0.3.5.dist-info/METADATA
pyxml2xpath-0.3.5.dist-info/WHEEL
pyxml2xpath-0.3.5.dist-info/entry_points.txt
pyxml2xpath-0.3.5.dist-info/top_level.txt
pyxml2xpath-0.3.5.dist-info/RECORD
