Metadata-Version: 2.4
Name: pyxml2xpath
Version: 0.3.5
Summary: Generate xpath expressions from XML document.
Author-email: Luis Muñoz <south.minds@gmail.com>
License-Expression: GPL-3.0
Project-URL: Repository, https://github.com/mluis7/pyxml2xpath.git
Keywords: xpath,xml
Classifier: Development Status :: 5 - Production/Stable
Classifier: Programming Language :: Python
Requires-Python: >=3.9
License-File: LICENSE
Requires-Dist: lxml
Dynamic: license-file
